LayerZero/AugmentationMode.py
LayerZero/GPUAugmentation.py
LayerZero/Helper.py
LayerZero/ImageDataLoader.py
LayerZero/KorniaHelper.py
LayerZero/Trainer.py
LayerZero/__init__.py
layerzero-0.4.3.dist-info/METADATA
layerzero-0.4.3.dist-info/WHEEL
layerzero-0.4.3.dist-info/top_level.txt
layerzero-0.4.3.dist-info/RECORD
