Metadata-Version: 2.4
Name: LayerZero
Version: 0.4.3
Summary: Build Pytorch Based NN Projects Faster
Author-email: Ujjwal Srivastava <recs.cse1645@gmail.com>
License: MIT
Requires-Python: >=3.8
Requires-Dist: torch
Requires-Dist: matplotlib
Requires-Dist: numpy
Requires-Dist: torchvision
Requires-Dist: requests
Requires-Dist: tqdm
Requires-Dist: tensorboard
Requires-Dist: torch-tb-profiler
